{
  "payment": {
    "merchant-account-id": {
      "value": "508b8896-b37d-4614-845c-26bf8bf2c948"
    },
    "request-id": "",
    "requested-amount": {
      "value": 10,
      "currency": "EUR"
    },
    "transaction-type": "purchase",
    "payment-methods": {
      "payment-method": [
        {
          "name": "creditcard"
        }
      ]
    },
    "three-d": {
      "attempt-three-d": "true"
    },
    "notifications": {
      "format": "application/xml",
      "notification": [
        {
          "url": "http://8e50a674.ngrok.io/wpp-integration-demo-php/src/result/notify.php"
        }
      ]
    },
    "success-redirect-url": "wpp-integration-demo-php/src/result/success.php",
    "fail-redirect-url": "wpp-integration-demo-php/src/result/fail.php",
    "cancel-redirect-url": "wpp-integration-demo-php/src/result/cancel.php"
  }
}
